{
    "skillSetData":[
        {
            "title": "Frontend",
            "description":"Proficiency in HTML5, CSS and JS ES8 and Vue. Also have experience with other technologies such as ASP.NET Blazor and React",
            "images":[
              {
                "src":"../assets/iconImages/HTML.png",
                "title":"HTML5",
                "alt":"Icon of HTML"
              },
              {
                "src":"../assets/iconImages/CSS.png",
                "title":"CSS",
                "alt":"Icon of CSS"
              },
              {
                "src":"../assets/iconImages/javascript.png",
                "title":"JavaScript",
                "alt":"Icon of JavaScript"
              },
              {
                "src":"../assets/iconImages/vue.png",
                "title":"Vue",
                "alt":"Icon of Vue"
              }
            ]
          },
          {
            "title": "Backend",
            "description":"I have been using Node and Spring Boot in numerous project,coupled with databases to create micro services.",
            "images":[
              {
                "src":"../assets/iconImages/node.png",
                "title":"Node",
                "alt":"Icon of Node"
              },
              {
                "src":"../assets/iconImages/springboot.png",
                "title":"Spring Boot",
                "alt":"Icon of Spring Boot"
              },
              {
                "src":"../assets/iconImages/MySQL.png",
                "title":"MySQL",
                "alt":"Icon of MySQL"
              },
              {
                "src":"../assets/iconImages/postman.png",
                "title":"Postman",
                "alt":"Icon of Postman"
              }
            ]
          },
          {
            "title": "UI/UX Design",
            "description":"Design is one of the most important aspects of any kind of user interface. I like a modern responsive look that feels alive when interacting.",
            "images":[
              {
                "src":"../assets/iconImages/figma.png",
                "title":"Figma",
                "alt":"Icon of Figma"
              },
              {
                "src":"../assets/iconImages/illustrator.png",
                "title":"Illustrator",
                "alt":"Icon of Illustrator"
              }
            ]
          },
          {
            "title": "Web Deployment",
            "description":"One of the most useful tools for deploying a web application is Nginx and Docker, which i have been using on a DO Linux VM.",
            "images":[
              {
                "src":"../assets/iconImages/nginx.png",
                "title":"NGINX",
                "alt":"Icon of NGINX"
              },
              {
                "src":"../assets/iconImages/docker.png",
                "title":"Docker",
                "alt":"Icon of Docker"
              },
              {
                "src":"../assets/iconImages/digitalOcean.png",
                "title":"DigitalOcean",
                "alt":"Icon of DigitalOcean"
              },
              {
                "src":"../assets/iconImages/MySQL.png",
                "title":"MySQL",
                "alt":"Icon of MySQL"
              }
            ]
          }
    ]
}